setup.cfg
setup.py
PyGraph.egg-info/PKG-INFO
PyGraph.egg-info/SOURCES.txt
PyGraph.egg-info/dependency_links.txt
PyGraph.egg-info/top_level.txt
pygraph/__init__.py
pygraph/exceptions.py
pygraph/predefined_graphs.py
pygraph/render.py
pygraph/classes/__init__.py
pygraph/classes/directed_graph.py
pygraph/classes/undirected_graph.py
pygraph/functions/__init__.py
pygraph/functions/biconnected_components.py
pygraph/functions/connected_components.py
pygraph/functions/spanning_tree.py
pygraph/functions/planarity/__init__.py
pygraph/functions/planarity/functions.py
pygraph/functions/planarity/kocay_algorithm.py
pygraph/functions/planarity/lipton-tarjan_algorithm.py
pygraph/functions/searching/__init__.py
pygraph/functions/searching/astar.py
pygraph/functions/searching/breadth_first_search.py
pygraph/functions/searching/depth_first_search.py
pygraph/helpers/__init__.py
pygraph/helpers/functions.py
pygraph/helpers/classes/__init__.py
pygraph/helpers/classes/disjoint_set.py
pygraph/helpers/classes/priority_queue.py
tests/__init__.py
tests/test_a_star_search.py
tests/test_bfs.py
tests/test_biconnected_components.py
tests/test_connected_components.py
tests/test_dfs.py
tests/test_directed_graph.py
tests/test_make_subgraph.py
tests/test_merge_graphs.py
tests/test_planarity.py
tests/test_spanning_tree.py
tests/test_undirected_graph.py
tests/utility_functions.py