Metadata-Version: 1.1
Name: PyGraph
Version: 0.2.1
Summary: A graph manipulation library in pure Python
Home-page: https://github.com/jciskey/pygraph
Author: Joe Ciskey
Author-email: forms@sleeplesshacker.com
License: MIT
Platform: UNKNOWN
Classifier: Development Status :: 2 - Pre-Alpha
Classifier: Intended Audience :: Developers
Classifier: License :: OSI Approved :: MIT License
Classifier: Natural Language :: English
Classifier: Operating System :: OS Independent
Classifier: Programming Language :: Python
Classifier: Programming Language :: Python :: 2.7
